deepai/__init__.py
deepai/_version.py
deepai/main.py
deepai-1.0.1.dist-info/LICENSE
deepai-1.0.1.dist-info/METADATA
deepai-1.0.1.dist-info/WHEEL
deepai-1.0.1.dist-info/top_level.txt
deepai-1.0.1.dist-info/RECORD
