Metadata-Version: 2.1
Name: deepai
Version: 1.0.1
Summary: Quantum Computer Library for Everyone
Home-page: https://github.com/DeepAI/DeepAI
Author: The DeepAI Developers
Author-email: info@deepai.com
License: Apache 2
Classifier: Programming Language :: Python :: 3
Classifier: License :: OSI Approved :: Apache Software License
Classifier: Development Status :: 3 - Alpha
License-File: LICENSE
